kyms/__init__.py
kyms/generated_podcast_mp3s/__init__.py
kyms/generated_podcast_scripts/__init__.py
kyms/LICENSE
kyms/main.py
kyms/music/__init__.py
kyms/music/bolero-161191.mp3
kyms/music/lofi-chill-medium-version-159456.mp3
kyms/music/scandinavianz-thessaloniki-free-download-173689.mp3
kyms/music/whistle-vibes-172471.mp3
kyms/prompts/__init__.py
kyms/prompts/podcast_ads.py
kyms/prompts/podcast_intro.py
kyms/prompts/podcast_outro.py
kyms/prompts/podcast_segment.py
kyms/prompts/podcast_segue.py
kyms/README.md
kyms/utils/__init__.py
kyms/utils/date_stuff.py
kyms/utils/eleven_labs_stuff.py
kyms/utils/open_ai_stuff.py
kyms/utils/string_stuff.py
kyms-1.0.0.dist-info/entry_points.txt
kyms-1.0.0.dist-info/LICENSE
kyms-1.0.0.dist-info/METADATA
kyms-1.0.0.dist-info/WHEEL
kyms-1.0.0.dist-info/RECORD
