Metadata-Version: 2.1
Name: kyms
Version: 1.0.0
Summary: A complete, AI-assisted Podcast solution! 
Home-page: https://www.keepyourmouthshut.net/
License: MIT
Keywords: openai,podcast,elevenlabs
Author: Rajtilak Bhattacharjee
Author-email: rajtilak.blog@gmail.com
Requires-Python: >=3.10,<4.0
Classifier: License :: OSI Approved :: MIT License
Classifier: Programming Language :: Python :: 3
Classifier: Programming Language :: Python :: 3.10
Classifier: Programming Language :: Python :: 3.11
Requires-Dist: elevenlabs (>=0.2.26,<0.3.0)
Requires-Dist: openai (>=1.1.1,<2.0.0)
Requires-Dist: pydub (>=0.25.1,<0.26.0)
Requires-Dist: pyyaml (>=6.0.1,<7.0.0)
Requires-Dist: typer[all] (>=0.9.0,<0.10.0)
Project-URL: Documentation, https://www.keepyourmouthshut.net/
Project-URL: Repository, https://github.com/rajtilakjee/kyms
